llrq/__init__.py
llrq/control.py
llrq/cvx_control.py
llrq/frequency_control.py
llrq/llrq_dynamics.py
llrq/mass_action_simulator.py
llrq/reaction_network.py
llrq/sbml_parser.py
llrq/solver.py
llrq/thermodynamic_accounting.py
llrq/visualization.py
llrq/estimation/__init__.py
llrq/estimation/kalman.py
llrq/integrations/__init__.py
llrq/integrations/mass_action_drive.py
llrq/ops/ltisolve.py
llrq/ops/time_varying.py
llrq/utils/__init__.py
llrq/utils/concentration_utils.py
llrq/utils/equilibrium_utils.py
llrq-0.0.3.dist-info/licenses/LICENSE
llrq-0.0.3.dist-info/METADATA
llrq-0.0.3.dist-info/WHEEL
llrq-0.0.3.dist-info/top_level.txt
llrq-0.0.3.dist-info/RECORD
