Metadata-Version: 2.4
Name: llrq
Version: 0.0.3
Summary: Log-Linear Reaction Quotient Dynamics: Tractable framework for chemical reaction networks
Author-email: Steven Diamond <steven@gridmatic.com>
License:                                  Apache License
Project-URL: Homepage, https://github.com/reactionquotient/llrq
Project-URL: Repository, https://github.com/reactionquotient/llrq
Project-URL: Issues, https://github.com/reactionquotient/llrq/issues
Keywords: reaction networks,systems biology,SBML,chemical kinetics,reaction quotient
Classifier: Development Status :: 3 - Alpha
Classifier: Intended Audience :: Science/Research
Classifier: License :: OSI Approved :: Apache Software License
Classifier: Programming Language :: Python :: 3
Classifier: Programming Language :: Python :: 3.8
Classifier: Programming Language :: Python :: 3.9
Classifier: Programming Language :: Python :: 3.10
Classifier: Programming Language :: Python :: 3.11
Classifier: Programming Language :: Python :: 3.12
Classifier: Topic :: Scientific/Engineering :: Bio-Informatics
Classifier: Topic :: Scientific/Engineering :: Chemistry
Classifier: Topic :: Scientific/Engineering :: Mathematics
Requires-Python: >=3.8
License-File: LICENSE
Requires-Dist: numpy>=1.20.0
Requires-Dist: scipy>=1.7.0
Requires-Dist: matplotlib>=3.3.0
Requires-Dist: python-libsbml>=5.19.0
Requires-Dist: tellurium>=2.2.0
Requires-Dist: cvxpy>=1.7.2
Provides-Extra: dev
Requires-Dist: pytest>=7.0; extra == "dev"
Requires-Dist: pytest-cov>=4.0; extra == "dev"
Requires-Dist: ruff>=0.6.0; extra == "dev"
Requires-Dist: mypy>=1.0; extra == "dev"
Requires-Dist: pre-commit>=3.0.0; extra == "dev"
Provides-Extra: test
Requires-Dist: pytest>=7.0; extra == "test"
Requires-Dist: pytest-cov>=4.0; extra == "test"
Requires-Dist: psutil>=5.9.0; extra == "test"
Dynamic: license-file
